[
        {
            "id": "dc3990ab-7ff8-48c9-8ddf-478fcdf0391a",
            "num": 1,
            "titulo": "Real Steel World Robot Boxing APK MOD v 94.94.116 Dinheiro Infinito",
            "subtitulo": "Uma nova parte do jogo de luta de robôs baseado no filme “Gigantes de Aço”",
            "imagem": "https://play-lh.googleusercontent.com/HwtIpzhGZND8PZhnV-QnzqBJ6Asn4HaOZwdpmrazyn--DWJS_Hx9WUh0Q7trx1x5aM6C=w428-h241-rw",
            "google_play_link": "https://play.google.com/store/apps/details?id=com.jumpgames.rswrb&hl=pt_BR",
            "mediafire_link": "https://www.mediafire.com/file/xrt9tjxitvydcgi/real-steel-world-robot-boxing-94.94.116-mod.apk/file",
            "descricao": "",
            "screenshots": [],
            "extra_text": "Moedas ilimitadas.",
            "categoria": "jogos"
        },

        {
        "id": "6798e5ca-bbea-469f-a9c0-2622c3a6d5c2",
        "num": 41,
        "titulo": "Grand Theft Auto: San Andreas APK MOD v 2.11.264 Dinheiro Infinito",
        "subtitulo": "Grand Theft Auto: San Andreas. Faça o download do GTA para Android",
        "imagem": "https://img.odcdn.com.br/wp-content/uploads/2021/08/GTA__San_Andreas.png",
        "google_play_link": "https://play.google.com/store/apps/details?id=com.rockstargames.gtasa",
        "mediafire_link": "https://modsfire.com/Bbt7fm14aq545y5",
        "descricao": "Grand Theft Auto: San Andreas APK MOD Dinheiro Infinito  – o porto oficial da famosa ação multiplayer da RockStar.Boa velocidade e sem vírus!No nosso site você pode facilmente baixar a versão mais recente Grand Theft Auto: San Andreas APK MOD Dinheiro Infinito.apk! Tudo sem registro e envio de SMS!",
        "screenshots": [],
        "extra_text": "2. Jogo salvo com quantidade ilimitada de moeda adicionada.",
        "categoria": "jogos"

        }

    ]